README.md
setup.cfg
setup.py
django_khipu.egg-info/PKG-INFO
django_khipu.egg-info/SOURCES.txt
django_khipu.egg-info/dependency_links.txt
django_khipu.egg-info/not-zip-safe
django_khipu.egg-info/requires.txt
django_khipu.egg-info/top_level.txt
khipu/__init__.py
khipu/admin.py
khipu/api.py
khipu/constants.py
khipu/exceptions.py
khipu/forms.py
khipu/models.py
khipu/signals.py
khipu/urls.py
khipu/views.py
khipu/migrations/0001_initial.py
khipu/migrations/__init__.py
khipu/services/__init__.py
khipu/services/banks.py
khipu/services/common.py
khipu/services/payments.py
khipu/services/tests/__init__.py
khipu/services/tests/test_common.py
khipu/services/tests/test_payments.py
khipu/tests/__init__.py
khipu/tests/test_api.py
khipu/tests/test_forms.py
khipu/tests/test_models.py
khipu/tests/test_views.py