Metadata-Version: 1.1
Name: django-khipu
Version: 1.0.0
Summary: Aplicación para integrar pagos Khipu en Django
Home-page: https://github.com/misalabs/django-khipu
Author: Misa G.
Author-email: hi@misalabs.com
License: MIT license
Keywords: django khipu chile
Platform: any
Classifier: Framework :: Django
Classifier: Intended Audience :: Developers
Classifier: Intended Audience :: System Administrators
Classifier: Environment :: Web Environment
Classifier: Topic :: Utilities
Classifier: Programming Language :: Python :: 2.7
